pytghaku/__init__.py
pytghaku/__version__.py
pytghaku/environment.py
pytghaku/exceptions.py
pytghaku/ffmpeg.py
pytghaku/filters.py
pytghaku/mtproto_required.py
pytghaku/mutex.py
pytghaku/pytghaku.py
pytghaku/pytghaku_session.py
pytghaku/scaffold.py
pytghaku/statictypes.py
pytghaku/sync.py
pytghaku/version_manager.py
pytghaku/ytdlp.py
pytghaku/custom_api/__init__.py
pytghaku/custom_api/custom_api.py
pytghaku/handlers/__init__.py
pytghaku/handlers/handlers_holder.py
pytghaku/media_devices/__init__.py
pytghaku/media_devices/device_info.py
pytghaku/media_devices/media_devices.py
pytghaku/media_devices/screen_info.py
pytghaku/methods/__init__.py
pytghaku/methods/calls/__init__.py
pytghaku/methods/calls/change_volume_call.py
pytghaku/methods/calls/get_participants.py
pytghaku/methods/calls/leave_call.py
pytghaku/methods/decorators/__init__.py
pytghaku/methods/decorators/on_update.py
pytghaku/methods/stream/__init__.py
pytghaku/methods/stream/mute_stream.py
pytghaku/methods/stream/pause_stream.py
pytghaku/methods/stream/play.py
pytghaku/methods/stream/played_time.py
pytghaku/methods/stream/resume_stream.py
pytghaku/methods/stream/unmute_stream.py
pytghaku/methods/utilities/__init__.py
pytghaku/methods/utilities/cache_peer.py
pytghaku/methods/utilities/call_holder.py
pytghaku/methods/utilities/compose.py
pytghaku/methods/utilities/cpu_usage.py
pytghaku/methods/utilities/idle.py
pytghaku/methods/utilities/ping.py
pytghaku/methods/utilities/resolve_chat_id.py
pytghaku/methods/utilities/run.py
pytghaku/methods/utilities/start.py
pytghaku/methods/utilities/stream_params.py
pytghaku/mtproto/__init__.py
pytghaku/mtproto/bridged_client.py
pytghaku/mtproto/client_cache.py
pytghaku/mtproto/haku_client.py
pytghaku/mtproto/hydrogram_client.py
pytghaku/mtproto/mtproto_client.py
pytghaku/mtproto/telethon_client.py
pytghaku/types/__init__.py
pytghaku/types/browsers.py
pytghaku/types/cache.py
pytghaku/types/dict.py
pytghaku/types/list.py
pytghaku/types/participant_list.py
pytghaku-2.0.2.dist-info/LICENSE
pytghaku-2.0.2.dist-info/METADATA
pytghaku-2.0.2.dist-info/WHEEL
pytghaku-2.0.2.dist-info/top_level.txt
pytghaku-2.0.2.dist-info/RECORD
