Metadata-Version: 2.1
Name: pytghaku
Version: 2.0.2
Summary: Async client API for the Telegram Calls.
Author-email: RizalDevs <rizaldaitona@gmail.com>
License: GNU LESSER GENERAL PUBLIC LICENSE
Project-URL: Homepage, https://pytghaku.github.io/
Project-URL: Repository, https://github.com/pytghaku/pytghaku.git
Project-URL: Documentation, https://pytghaku.github.io/PyTgCalls
Project-URL: Changelog, https://pytghaku.github.io/PyTgCalls/Changelogs
Keywords: audio,python,library,video,telegram,stream,ffmpeg,cpp,webrtc,voice-chat,voip,group-chat,video-calls,calls,video-chat,pytghaku,ntgcalls,tgcalls,py-tgcalls,haku,telethon,hydrogram
Classifier: License :: OSI Approved :: GNU Lesser General Public License v3 (LGPLv3)
Classifier: Operating System :: OS Independent
Classifier: Programming Language :: Python :: 3
Classifier: Programming Language :: Python :: 3 :: Only
Classifier: Programming Language :: Python :: 3.8
Classifier: Programming Language :: Python :: 3.9
Classifier: Programming Language :: Python :: 3.10
Classifier: Programming Language :: Python :: 3.11
Classifier: Programming Language :: Python :: 3.12
Requires-Python: >=3.8
License-File: LICENSE
Requires-Dist: aiohttp (>=3.9.3)
Requires-Dist: ntgcalls (>=1.2.0)
Requires-Dist: psutil
Requires-Dist: screeninfo
Requires-Dist: deprecation
Provides-Extra: haku
Requires-Dist: haku (==1.0) ; extra == 'haku'
Provides-Extra: hydrogram
Requires-Dist: hydrogram (>=0.1.4) ; extra == 'hydrogram'
Provides-Extra: telethon
Requires-Dist: telethon (>=1.24.0) ; extra == 'telethon'
